sendle_lib/__init__.py
sendle_lib/order_cancel_response.py
sendle_lib/order_request.py
sendle_lib/order_response.py
sendle_lib/products_response.py
sendle_lib/rating.py
sendle_lib/tracking_response.py
sendle_lib/validation_error.py
carrier.sendle-2023.1.12.dist-info/METADATA
carrier.sendle-2023.1.12.dist-info/WHEEL
carrier.sendle-2023.1.12.dist-info/top_level.txt
carrier.sendle-2023.1.12.dist-info/RECORD
